gimei/__init__.py
gimei/address.py
gimei/gimei.py
gimei/name.py
gimei/data/addresses.yml
gimei/data/names.yml
tests/__init__.py
tests/test_address.py
tests/test_name.py
gimei-0.2.3.dist-info/LICENSE
gimei-0.2.3.dist-info/METADATA
gimei-0.2.3.dist-info/WHEEL
gimei-0.2.3.dist-info/top_level.txt
gimei-0.2.3.dist-info/RECORD
