Metadata-Version: 2.1
Name: gimei
Version: 0.2.3
Summary: generates the name and the address at random.
Home-page: https://github.com/nabetama/gimei
Author: Mao Nabeta
Author-email: mao.nabeta@gmail.com
License: UNKNOWN
Keywords: gimei,name,random
Platform: UNKNOWN
Classifier: Development Status :: 3 - Alpha
Classifier: Intended Audience :: Developers
Classifier: License :: OSI Approved :: MIT License
Classifier: Operating System :: OS Independent
Classifier: Programming Language :: Python
Classifier: Programming Language :: Python :: 3
Classifier: Topic :: Communications :: Chat
Classifier: Topic :: Software Development :: Libraries
Classifier: Topic :: Software Development :: Libraries :: Python Modules
Provides: gimei
Provides: name
Provides: random
Requires-Dist: pyyaml
